ar_ex_sys_worker-2.1.0.dist-info/licenses/LICENSE
ar_external_sys_worker/__init__.py
ar_external_sys_worker/main.py
ar_external_sys_worker/mixins.py
ar_external_sys_worker/tests/__init__.py
ar_external_sys_worker/tests/main_test.py
ar_external_sys_worker/tests/mixins_test.py
ar_ex_sys_worker-2.1.0.dist-info/METADATA
ar_ex_sys_worker-2.1.0.dist-info/WHEEL
ar_ex_sys_worker-2.1.0.dist-info/top_level.txt
ar_ex_sys_worker-2.1.0.dist-info/RECORD
