Metadata-Version: 2.4
Name: ar_ex_sys_worker
Version: 2.1.0
Author: PunchyArchy
Author-email: ksmdrmvscthny@gmail.com
License-File: LICENSE
Requires-Dist: requests
Requires-Dist: wsqluse>=1.85
Requires-Dist: pytz
Requires-Dist: tzlocal
Dynamic: author
Dynamic: author-email
Dynamic: description
Dynamic: license-file
Dynamic: requires-dist
